type2nc/__init__.py
type2nc/type2nc.py
type2nc/locales/de/LC_MESSAGES/messages.mo
type2nc/locales/en/LC_MESSAGES/messages.mo
type2nc/templates/demo_pgm_template_conventional.H
type2nc/templates/demo_pgm_template_cycle.H
type2nc/templates/pgm_foot_template.H
type2nc/templates/pgm_head_template.H
type2nc-0.6.3.data/scripts/type2nc.py
type2nc-0.6.3.dist-info/LICENSE
type2nc-0.6.3.dist-info/METADATA
type2nc-0.6.3.dist-info/WHEEL
type2nc-0.6.3.dist-info/top_level.txt
type2nc-0.6.3.dist-info/RECORD
