Metadata-Version: 2.1
Name: type2nc
Version: 0.6.3
Summary: convert truetype fonts to klartext nc-code
Home-page: https://github.com/drunsinn/type2nc
Author: drunsinn et al.
Author-email: dr.unsinn@googlemail.com
License: MIT
Keywords: cnc klartext font freetype
Platform: UNKNOWN
Classifier: Programming Language :: Python :: 3
Classifier: Development Status :: 4 - Beta
Classifier: License :: OSI Approved :: MIT License
Classifier: Operating System :: OS Independent
License-File: LICENSE
Requires-Dist: numpy (>=1.6.2)
Requires-Dist: scipy (>=0.19.0)
Requires-Dist: freetype-py (>=1.1)
Requires-Dist: argparse (>=1.4.0)
Requires-Dist: Hershey-Fonts (>=2.1.0)
